[
    { "_id":1, "name": "JobSeeker - Single", "payment":"620.80", "type": "JS" },
    {"_id": 2, "name": "JobSeeker - Single, with dependent", "payment":"667.50", "type": "JS" },
    {"_id": 3, "name": "JobSeeker - Partnered", "payment":"565.40", "type": "JS" },
    {"_id": 4, "name": "Austudy - No Children", "payment":"512.50", "type": "AS" },
    {"_id": 5, "name": "Austudy - Single, with children", "payment":"656.00", "type": "AS" },
    {"_id": 6, "name": "Austudy - partnered, with children", "payment":"557.90", "type": "AS" },
    {"_id": 7, "name": "Youth Allowance - Single, no children, 18+, live with parents", "payment":"354.60", "type": "YA" },
    {"_id": 8, "name": "Youth Allowance - Single, no children, 18+, live out of home", "payment":"512.50", "type": "YA" },
    {"_id": 9, "name": "Youth Allowance - Single, with children", "payment":"656.00", "type": "YA" },
    {"_id": 10, "name": "Youth Allowance - Partnered, no children", "payment":"512.50", "type": "YA" },
    {"_id": 11, "name": "Youth Allowance - Partnered, with children ", "payment":"557.90", "type": "YA" }
   
]